pymarsys/__init__.py
pymarsys/async_pymarsys.py
pymarsys/base_endpoint.py
pymarsys/connections.py
pymarsys/contact.py
pymarsys/contact_field.py
pymarsys/contacts.py
pymarsys/emarsys.py
pymarsys/exception.py
pymarsys/pymarsys.py
pymarsys/sync_pymarsys.py
pymarsys/sync_pymarsys_old.py
pymarsys/sync/__init__.py
pymarsys/sync/base_endpoint.py
pymarsys/sync/contact.py
pymarsys/sync/sync_emarsys.py
pymarsys-0.0.1.dev0.dist-info/DESCRIPTION.rst
pymarsys-0.0.1.dev0.dist-info/METADATA
pymarsys-0.0.1.dev0.dist-info/RECORD
pymarsys-0.0.1.dev0.dist-info/WHEEL
pymarsys-0.0.1.dev0.dist-info/metadata.json
pymarsys-0.0.1.dev0.dist-info/top_level.txt
