Metadata-Version: 2.0
Name: pymarsys
Version: 0.0.1.dev0
Summary: A Python client for the Emarsys API
Home-page: http://github.com/transcovo/pymarsys/
Author: Transcovo
Author-email: tech-data@chauffeur-prive.com
License: Apache 2.0
Platform: UNKNOWN
Classifier: Development Status :: 2 - Pre-Alpha
Classifier: Intended Audience :: Developers
Classifier: Natural Language :: English
Classifier: License :: OSI Approved :: Apache Software License
Classifier: Programming Language :: Python
Classifier: Programming Language :: Python :: 3
Classifier: Programming Language :: Python :: 3.4
Classifier: Programming Language :: Python :: 3.5
Requires-Dist: requests (>=2.12.1)
Requires-Dist: aiohttp (>=1.2.0)
